{"digest":"43131d6d09de749b22910990e993909475bfc8eb","css":".sheet-container .sheet-toolbar .btn-toolbar img.content-mask {\n  background-color: #f6f6f6;\n}\n.sheet-container .sheet-toolbar .sheet-toolbar-container {\n  background-image: -webkit-linear-gradient(top, #51504a, #34332f);\n  box-shadow: none;\n}\n.sheet-container .sheet-toolbar .sheet-toolbar-container .btn {\n  background: #4c4b45;\n}\n.sheet-container .sheet-toolbar .sheet-toolbar-container .btn.btn-toolbar {\n  color: #f6f6f6;\n}\n.sheet-container .sheet-toolbar .sheet-toolbar-container .toolbar-activity .activity-toolbar-icon {\n  background: #f6f6f6;\n}\n.sheet-container .sheet-toolbar .item-back img.content-mask,\n.sheet-container .sheet-toolbar .toolbar-menu-control img.content-mask {\n  background-color: #f6f6f6;\n}\n.sheet-container .sheet-toolbar .item-back .item-back-title {\n  color: #f6f6f6;\n}\n.sheet-container .sheet-toolbar .selection-bar .absolute {\n  border-color: #4e4d47;\n  background-color: #2c2b28;\n}\n.sheet-container .sheet-toolbar .selection-bar .absolute .inner .centered {\n  color: #f6f6f6;\n}\n.btn-icon img.content-mask {\n  background-color: #f6f6f6;\n  color: #f6f6f6;\n}\n.btn-icon img.content-mask:hover {\n  background-color: #f07746;\n}\nbody.is-blurred .sheet-container .sheet-toolbar .sheet-toolbar-container {\n  background-image: -webkit-linear-gradient(top, #34332f, #34332f);\n}\n.find-in-thread {\n  background: #f6f6f6;\n  text-align: right;\n  overflow: hidden;\n  height: 0;\n  padding: 0 8px;\n  transition: all 125ms ease-in-out;\n  border-bottom: 0;\n}\n.find-in-thread.enabled {\n  padding: 4px 8px;\n  height: 35px;\n  border-bottom: 1px solid #ffffff;\n}\n.find-in-thread .controls-wrap {\n  display: inline-block;\n}\n.find-in-thread .selection-progress {\n  color: rgba(35, 31, 32, 0.5);\n  position: absolute;\n  top: 4px;\n  right: 54px;\n  font-size: 12px;\n}\n.find-in-thread .btn.btn-find-in-thread {\n  border: 0;\n  box-shadow: 0 0 0;\n  border-radius: 0;\n  background: transparent;\n  display: inline-block;\n}\n.find-in-thread .input-wrap {\n  display: inline-block;\n  position: relative;\n}\n.find-in-thread .input-wrap input {\n  height: 26px;\n  width: 230px;\n  padding-left: 8px;\n  font-size: 12px;\n}\n.find-in-thread .input-wrap .btn-wrap {\n  min-width: 54px;\n  position: absolute;\n  top: 0;\n  right: 0;\n}\n","imports":[{"path":"internal_packages/ui-ubuntu/styles/ui-variables.less","digest":"1e25537cac5618bb47c505557274ca8e52edfbbc"},{"path":"static/base/ui-variables.less","digest":"a95f78aa1bc678e04a9da0f71fadb4a0ea190588"}],"version":1}